rlhelper/__init__.py
rlhelper-0.52.dist-info/LICENSE
rlhelper-0.52.dist-info/METADATA
rlhelper-0.52.dist-info/WHEEL
rlhelper-0.52.dist-info/top_level.txt
rlhelper-0.52.dist-info/RECORD
