Metadata-Version: 2.1
Name: rlhelper
Version: 0.52
Summary: Shortcut functions for canvas strings and spacing objects. Inputs must be * 72 (inch)
Home-page: https://bitbucket.org/mikeronni/rlhelper
Author: Michael Lance
Author-email: michael.lance@gmail.com
License: MIT
License-File: LICENSE
